odoo10_addon_stock_ownership_by_move-10.0.0.1.0-py2.7-nspkg.pth
odoo/addons/stock_ownership_by_move/README.rst
odoo/addons/stock_ownership_by_move/__init__.py
odoo/addons/stock_ownership_by_move/__manifest__.py
odoo/addons/stock_ownership_by_move/model/__init__.py
odoo/addons/stock_ownership_by_move/model/picking.py
odoo/addons/stock_ownership_by_move/security/group.xml
odoo/addons/stock_ownership_by_move/tests/__init__.py
odoo/addons/stock_ownership_by_move/tests/test_picking_to_pack_ops.py
odoo/addons/stock_ownership_by_move/view/move.xml
odoo/addons/stock_ownership_by_move/view/picking.xml
odoo/addons/stock_ownership_by_move/view/wizard_transfer.xml
odoo10_addon_stock_ownership_by_move-10.0.0.1.0.dist-info/DESCRIPTION.rst
odoo10_addon_stock_ownership_by_move-10.0.0.1.0.dist-info/METADATA
odoo10_addon_stock_ownership_by_move-10.0.0.1.0.dist-info/RECORD
odoo10_addon_stock_ownership_by_move-10.0.0.1.0.dist-info/WHEEL
odoo10_addon_stock_ownership_by_move-10.0.0.1.0.dist-info/metadata.json
odoo10_addon_stock_ownership_by_move-10.0.0.1.0.dist-info/namespace_packages.txt
odoo10_addon_stock_ownership_by_move-10.0.0.1.0.dist-info/top_level.txt
